setup.cfg
setup.py
drivar/Drivar.py
drivar/DrivarAdafruitDCMotorHat.py
drivar/DrivarHolonomic.py
drivar/DrivarNoop.py
drivar/DrivarNxt.py
drivar/__init__.py
drivar.egg-info/PKG-INFO
drivar.egg-info/SOURCES.txt
drivar.egg-info/dependency_links.txt
drivar.egg-info/requires.txt
drivar.egg-info/top_level.txt