Metadata-Version: 1.0
Name: drivar
Version: 0.2.5
Summary: Hardware abstraction layer for Raspbuggy
Home-page: https://github.com/cmcrobotics/raspbuggy
Author: Brice Copy
Author-email: brice.copy@gmail.com
License: UNKNOWN
Keywords: raspbuggy
Platform: UNKNOWN
